[
    {
        "title": "Бухгалтер по реализациям",
        "description": "45 000 – 70 000₽на руки / Опыт 1-3 года / ОООНефтегазстрой"
    },
    {
        "title": "Персональный (семейный) водитель руководителя",
        "description": "от80 000₽на руки / Опыт 3-6 лет / ОООСпектр-Пак Юг"
    },
    {
        "title": "Оператор на телефоне (удаленно)",
        "description": "Опыт 1-3 года / от56 000₽до вычета налогов / Опыт 1-3 года"
    },
    {
        "title": "Специалист по приему заказов (интернет-магазин)",
        "description": "Без опыта / 65 000 – 90 000₽на руки / Без опыта"
    },
    {
        "title": "Менеджер по работе с клиентами (без продаж)",
        "description": "Без опыта / 60 000 – 100 000₽до вычета налогов / Без опыта"
    },
    {
        "title": "Менеджер Wildberries",
        "description": "Опыт 1-3 года / от100 000₽на руки / Опыт 1-3 года"
    },
    {
        "title": "Помощник руководителя-старший администратор",
        "description": "Без опыта / 120 000 – 160 000₽на руки / ОООMAVR"
    },
    {
        "title": "Операционный директор",
        "description": "Опыт более 6 лет / 200 000 – 1 000 000₽до вычета налогов / ИПАйзятов Марат Растямович"
    },
    {
        "title": "Учитель физической культуры",
        "description": "Опыт 1-3 года / от110 000₽до вычета налогов / ГБОУ школа №1584"
    },
    {
        "title": "Тестировщик",
        "description": "Опыт 1-3 года / от180 000₽до вычета налогов / Опыт 1-3 года"
    },
    {
        "title": "Водитель-испытатель",
        "description": "Опыт более 6 лет / от90 000₽до вычета налогов / ООООранж Драйв Инжиниринг"
    },
    {
        "title": "Сотрудник склада (д. Коледино)",
        "description": "Без опыта / 87 000 – 120 000₽на руки / WILDBERRIES"
    },
    {
        "title": "Охранник в частный дом (УЧО 6 разряда)",
        "description": "Опыт 1-3 года / 150 000 – 200 000₽на руки / Легис безопасность"
    },
    {
        "title": "Кладовщик",
        "description": "Без опыта / 150 000 – 180 000₽на руки / WILDBERRIES"
    },
    {
        "title": "Системный администратор",
        "description": "Без опыта / от100 000₽на руки / ОООВелта Ойл"
    },
    {
        "title": "Личный ассистент / Руководитель ассистентов",
        "description": "Опыт 1-3 года / 250 000 – 350 000₽на руки / Компания Апогей (1С-франчайзи)"
    },
    {
        "title": "Комплектовщик на склад М/Ж не ТЯЖЁЛАЯ РАБОТА",
        "description": "Без опыта / 196 000 – 499 999₽на руки / Без опыта"
    },
    {
        "title": "Менеджер по подбору персонала",
        "description": "Без опыта / от100 000₽на руки / ОООБертэн"
    },
    {
        "title": "Менеджер по документообороту",
        "description": "Без опыта / от50 000₽на руки / ОООРарс Медиа"
    },
    {
        "title": "Ассистент в рекламное агентство",
        "description": "Без опыта / от70 000₽на руки / ОООЗолотое Звено"
    },
    {
        "title": "Ведущий инженер по лесопользованию",
        "description": "ОООФорестГранд / Опыт 1-3 года / Спасск-Дальний"
    },
    {
        "title": "Товаровед",
        "description": "58 000 – 83 200₽до вычета налогов / Без опыта / Самокат (ООО Умный ритейл)"
    },
    {
        "title": "Менеджер по международному туризму",
        "description": "Опыт 1-3 года / 70 000 – 200 000₽до вычета налогов / ОООИндивидуальный Туризм"
    },
    {
        "title": "Удалённый менеджер по подбору водителей",
        "description": "Опыт 1-3 года / 90 000 – 150 000₽на руки / Опыт 1-3 года"
    },
    {
        "title": "HR-менеджер в единственном лице / HR BP",
        "description": "Опыт 3-6 лет / 130 000 – 150 000₽на руки / Ремесленная пекарня Иван да Федор"
    },
    {
        "title": "Помощник по хозяйству на ферму",
        "description": "Без опыта / 195 000 – 298 000₽до вычета налогов / Без опыта"
    },
    {
        "title": "Финансовый менеджер",
        "description": "Опыт 1-3 года / от130 000₽на руки / ОООВелта Ойл"
    },
    {
        "title": "Охранник 6 разряд",
        "description": "Без опыта / 63 000 – 145 000₽на руки / ОООЧастная Охранная организация Специальные Технологии Безопасности"
    },
    {
        "title": "Водитель-экспедитор на автомобиле компании",
        "description": "Без опыта / 100 000 – 130 000₽на руки / Великоросс"
    },
    {
        "title": "Тестировщик роборуки",
        "description": "Без опыта / 50 000 – 68 000₽на руки / Яндекс Крауд: Качество продуктов"
    },
    {
        "title": "Модератор объявлений",
        "description": "Опыт 1-3 года / 45 200 – 54 200₽до вычета налогов / Опыт 1-3 года"
    },
    {
        "title": "Менеджер IT проектов",
        "description": "Опыт 1-3 года / 120 000 – 200 000₽до вычета налогов / ОООКолл-Тулз"
    },
    {
        "title": "Менеджер кондитерской",
        "description": "Без опыта / 90 000 – 96 000₽на руки / ОООПЕКР"
    },
    {
        "title": "Оператор ПК",
        "description": "Без опыта / 60 000 – 95 000₽на руки / Белый Лайнер"
    },
    {
        "title": "Официант",
        "description": "Без опыта / 140 000 – 180 000₽на руки / ОООБарсити"
    },
    {
        "title": "Охранник, г. Санкт-Петербург",
        "description": "Без опыта / от92 500₽на руки / Агентство безопасности Контрольный Пост"
    },
    {
        "title": "Менеджер по продажам",
        "description": "Опыт 1-3 года / 150 000 – 400 000₽на руки / ОООТранссвязь"
    },
    {
        "title": "Менеджер по работе с клиентами",
        "description": "Без опыта / 50 000 – 100 000₽на руки / Без опыта"
    },
    {
        "title": "Бариста",
        "description": "Опыт 1-3 года / 85 000 – 95 000₽на руки / Кофейня Sly Fox"
    },
    {
        "title": "Дизайнер-визуализатор",
        "description": "Опыт 1-3 года / 90 000 – 180 000₽на руки / ОООВК Мирэкс"
    },
    {
        "title": "SMM-менеджер",
        "description": "55 000 – 70 000₽на руки / Опыт 1-3 года / Доставка Kaifa (ИП Селезнев Денис Сергеевич)"
    },
    {
        "title": "Ведущий инженер по лесопользованию",
        "description": "ОООФорестГранд / Опыт 1-3 года / Спасск-Дальний"
    },
    {
        "title": "Администратор салона красоты",
        "description": "Без опыта / 40 000 – 60 000₽на руки / ИПДоброва Анжела Андреевна"
    },
    {
        "title": "Сборщик заказов",
        "description": "Без опыта / 80 000 – 100 000₽на руки / ОООФК ПУЛЬС"
    },
    {
        "title": "Менеджер по продажам (исходящие звонки, без поиска клиентов)",
        "description": "Без опыта / 75 000 – 150 000₽на руки / Без опыта"
    },
    {
        "title": "Фотограф - ретушер",
        "description": "Опыт 1-3 года / от80 000₽на руки / СИМБАТ"
    },
    {
        "title": "Менеджер объекта по клинингу",
        "description": "Опыт 1-3 года / 120 000₽на руки / ОМС"
    },
    {
        "title": "Территориальный менеджер",
        "description": "Опыт 1-3 года / 100 000 – 150 000₽на руки / ООООптимальный Путь"
    },
    {
        "title": "Шлифовщик бериллиевой керамики",
        "description": "Опыт 1-3 года / от150 000₽до вычета налогов / АОНПП Алмаз"
    },
    {
        "title": "Менеджер в детскую онлайн-школу",
        "description": "Без опыта / 70 000 – 110 000₽на руки / Без опыта"
    },
    {
        "title": "Менеджер клиентской поддержки (не продажи)",
        "description": "Без опыта / от70 000₽на руки / Dalli служба доставки"
    },
    {
        "title": "Оператор call-центра (специалист контактного центра)",
        "description": "Опыт 1-3 года / 52 800 – 90 000₽на руки / Опыт 1-3 года"
    },
    {
        "title": "Охранник (в Москве)",
        "description": "Без опыта / 77 500 – 135 000₽на руки / Без опыта"
    },
    {
        "title": "Офис-менеджер",
        "description": "Без опыта / 44 850 – 54 000₽до вычета налогов / ПАО «Промсвязьбанк», Старт карьеры"
    },
    {
        "title": "Водитель-курьер на машине компании",
        "description": "Без опыта / 170 000 – 270 000₽на руки / GDel"
    },
    {
        "title": "Продавец-консультант (м. Ленинский проспект)",
        "description": "Без опыта / 70 000 – 75 000₽до вычета налогов / Подружка, сеть магазинов"
    },
    {
        "title": "Курьер документов и посылок",
        "description": "Без опыта / 105 000 – 159 000₽на руки / Dostavista.ru служба доставки"
    },
    {
        "title": "Senior UX/UI-дизайнер",
        "description": "Опыт 3-6 лет / 300 000 – 370 000₽на руки / Dream Job"
    },
    {
        "title": "Официант",
        "description": "Без опыта / от120 000₽на руки / Вареничная №1 (Захарова Наталья)"
    },
    {
        "title": "Специалист по информационной безопасности",
        "description": "Опыт 1-3 года / до180 000₽до вычета налогов / ПАОМГКЛ"
    },
    {
        "title": "Грузчик",
        "description": "от60 000₽на руки / Без опыта / ИППлатонов Григорий Александрович"
    },
    {
        "title": "Директор региональных продаж",
        "description": "от250 000₽на руки / Опыт 3-6 лет / ОООГК Движение"
    },
    {
        "title": "Водитель на автомобиль компании",
        "description": "Без опыта / до250 000₽на руки / ИПХлопков Ювеналий Вячеславович"
    },
    {
        "title": "Хостес",
        "description": "Без опыта / 39 000 – 45 000₽на руки / ИПМиндюк Юлия Хоязитдиновна"
    },
    {
        "title": "Охранник склада с питанием / без лицензии",
        "description": "Без опыта / от105 000₽на руки / Агентство безопасности Контрольный Пост"
    },
    {
        "title": "Младший менеджер по B2B-продажам",
        "description": "Без опыта / от130 000₽на руки / ОООMindbox"
    },
    {
        "title": "Оператор контакт-центра (удаленно)",
        "description": "Без опыта / 60 000 – 100 000₽до вычета налогов / Без опыта"
    },
    {
        "title": "Мастер-приёмщик",
        "description": "Опыт 3-6 лет / 110 000 – 150 000₽на руки / "
    },
    {
        "title": "Конструктор мебельного производства",
        "description": "Опыт 3-6 лет / от150 000₽на руки / ОООNorton"
    },
    {
        "title": "Менеджер по продажам информационных продуктов",
        "description": "Опыт 3-6 лет / 150 000 – 250 000₽на руки / Опыт 3-6 лет"
    },
    {
        "title": "Продавец-консультант в магазин Lucky Bear (ТЦ \"Европейский\")",
        "description": "Без опыта / от65 000₽на руки / "
    },
    {
        "title": "Продавец-консультант магазина Street Beat в ТЦ Аутлет XL",
        "description": "Без опыта / 50 000 – 90 000₽на руки / Inventive Retail Group, Старт Карьеры, Street Beat"
    },
    {
        "title": "Главный бухгалтер",
        "description": "Опыт более 6 лет / 100 000 – 200 000₽до вычета налогов / ОООАвто-Хэлп"
    },
    {
        "title": "Менеджер в копицентр CRM",
        "description": "Опыт 1-3 года / 85 000 – 125 000₽на руки / "
    },
    {
        "title": "Сборщик заказов",
        "description": "Без опыта / до163 120₽на руки / Самокат (ООО Лидер консалт - официальный партнер)"
    },
    {
        "title": "Продавец-консультант Intimissimi на неполный день (Москва)",
        "description": "Без опыта / от60 000₽до вычета налогов / Oniverse"
    },
    {
        "title": "Бухгалтер на первичную документацию",
        "description": "Опыт 1-3 года / от80 000₽на руки / ОООЕвротест"
    },
    {
        "title": "Оператор на производство",
        "description": "Без опыта / до100 000₽на руки / Santek"
    },
    {
        "title": "Курьер подарков",
        "description": "Без опыта / до280 750₽на руки / Точка 299"
    },
    {
        "title": "Хостес",
        "description": "Без опыта / 80 000 – 90 000₽на руки / ОООБарсити"
    },
    {
        "title": "Грузчик",
        "description": "от60 000₽на руки / Без опыта / ИППлатонов Григорий Александрович"
    },
    {
        "title": "Директор региональных продаж",
        "description": "от250 000₽на руки / Опыт 3-6 лет / ОООГК Движение"
    },
    {
        "title": "Бариста",
        "description": "Без опыта / до99 990₽на руки / PIMS (ИП Босхомджиев Улюмджи Хейчиевич)"
    },
    {
        "title": "Оператор call-центра (удалённо)",
        "description": "Без опыта / 50 000 – 80 000₽до вычета налогов / Без опыта"
    },
    {
        "title": "Supply Chain Manager / Менеджер по логистике",
        "description": "Без опыта / от155 000₽до вычета налогов / «Procter & Gamble», Молодой специалист"
    },
    {
        "title": "Консультант интернет-магазина",
        "description": "Опыт 1-3 года / 70 000 – 90 000₽до вычета налогов / ЦУМ"
    },
    {
        "title": "Водитель",
        "description": "Опыт 1-3 года / 160 000 – 220 000₽на руки / ОООАрмада"
    },
    {
        "title": "R&D Product Registration Coordinator / Координатор по регистрации товаров и соблюдению нормативов",
        "description": "Без опыта / от95 000₽до вычета налогов / «Procter & Gamble», Опытный специалист"
    },
    {
        "title": "Официант",
        "description": "Без опыта / от130 000₽на руки / Joki Joya"
    },
    {
        "title": "Заведующий хозяйством",
        "description": "Без опыта / от41 000₽на руки / "
    },
    {
        "title": "Кладовщик",
        "description": "Без опыта / 150 000 – 180 000₽до вычета налогов / WILDBERRIES"
    },
    {
        "title": "Аналитик-консультант 1С",
        "description": "Опыт 1-3 года / от300 000₽до вычета налогов / Опыт 1-3 года"
    },
    {
        "title": "Менеджер call-центра",
        "description": "Без опыта / 140 000 – 200 000₽на руки / ОООЮрал Трэйд"
    },
    {
        "title": "Ведущий Системный администратор",
        "description": "Опыт 3-6 лет / 80 000 – 130 000₽на руки / ОООМК Компани Трейд"
    },
    {
        "title": "Кладовщик",
        "description": "Без опыта / 92 000 – 130 000₽до вычета налогов / ООО«ОФИСМАГ», Оптовое направление"
    },
    {
        "title": "Сборщик (аптечный склад)",
        "description": "Без опыта / 65 000 – 110 000₽на руки / ОООФК ПУЛЬС"
    },
    {
        "title": "Оператор чата на входящие обращения",
        "description": "Без опыта / 60 000 – 70 000₽на руки / ОООМКК М-Деньги"
    },
    {
        "title": "Курьер подарков",
        "description": "Без опыта / до280 750₽на руки / Точка 299"
    },
    {
        "title": "HR / Менеджер по подбору персонала",
        "description": "Без опыта / 80 000 – 120 000₽на руки / ОООЕвроОбувь"
    },
    {
        "title": "Грузчик чипсов и сухариков",
        "description": "Без опыта / 225 000 – 310 000₽на руки / Без опыта"
    }
]